LICENSE.txt
README.md
setup.py
MITunaX.egg-info/PKG-INFO
MITunaX.egg-info/SOURCES.txt
MITunaX.egg-info/dependency_links.txt
MITunaX.egg-info/requires.txt
MITunaX.egg-info/top_level.txt
flaskapp/__init__.py
flaskapp/app.py
flaskapp/example_app.py
flaskapp/setup.py
tuna/__init__.py
tuna/abort.py
tuna/analyze_parse_db.py
tuna/build_driver_cmd.py
tuna/builder.py
tuna/config_type.py
tuna/connection.py
tuna/corrupt_configs.py
tuna/data_migration_updated_layouts.py
tuna/db_engine.py
tuna/db_tables.py
tuna/driver_base.py
tuna/driver_bn.py
tuna/driver_conv.py
tuna/evaluator.py
tuna/export_configs.py
tuna/export_db.py
tuna/fin_builder.py
tuna/fin_class.py
tuna/fin_eval.py
tuna/fin_utils.py
tuna/find_db.py
tuna/flask.py
tuna/flask_example.py
tuna/go_fish.py
tuna/grafana_dict.py
tuna/helper.py
tuna/import_configs.py
tuna/import_db.py
tuna/load_job.py
tuna/machine.py
tuna/machine_management_interface.py
tuna/metadata.py
tuna/metrics.py
tuna/miopen_db_helpers.py
tuna/miopen_tables.py
tuna/parse_args.py
tuna/parsing.py
tuna/prune_db.py
tuna/query_db.py
tuna/rm_dup_cfgs.py
tuna/rm_dup_jobs.py
tuna/session.py
tuna/solver_res.py
tuna/sql.py
tuna/sqlite_2txt.py
tuna/tables.py
tuna/worker_interface.py
tuna/dbBase/__init__.py
tuna/dbBase/base_class.py
tuna/dbBase/sql_alchemy.py
tuna/miopen/__init__.py
tuna/utils/__init__.py
tuna/utils/db_utility.py
tuna/utils/dupe_resolve.py
tuna/utils/logger.py
tuna/utils/merge_db.py
tuna/utils/utility.py