Metadata-Version: 2.1
Name: MITunaX
Version: 0.1
Summary: Tuna is a distributed tuning infrastructure that provides pre-compiled kernels for MIOpen customers through automated Jenkins pipelines and SLURM scalable architecture.
Home-page: https://github.com/ROCmSoftwarePlatform/MITunaX.git
License: MIT
License-File: LICENSE.txt
